core/__init__.py
core/model_training.py
core/tensor_operations.py
pasla-0.2.dist-info/LICENSE
pasla-0.2.dist-info/METADATA
pasla-0.2.dist-info/WHEEL
pasla-0.2.dist-info/plain.txt
pasla-0.2.dist-info/top_level.txt
pasla-0.2.dist-info/RECORD
